{"nm":"1_boat","ddd":0,"h":300,"w":375,"meta":{"g":"@lottiefiles/toolkit-js 0.33.2"},"layers":[{"ty":4,"nm":"Shape Layer 2","sr":1,"st":96,"op":192,"ip":96,"hd":false,"ddd":0,"bm":0,"hasMask":false,"td":1,"ao":0,"ks":{"a":{"a":0,"k":[0,0,0],"ix":1},"s":{"a":0,"k":[100,100,100],"ix":6},"sk":{"a":0,"k":0},"p":{"a":1,"k":[{"o":{"x":0.333,"y":0},"i":{"x":0.667,"y":1},"s":[187.5,152.25,0],"t":96,"ti":[-22.667,0.083,0],"to":[22.667,-0.083,0]},{"s":[323.5,151.75,0],"t":174}],"ix":2},"r":{"a":0,"k":0,"ix":10},"sa":{"a":0,"k":0},"o":{"a":0,"k":100,"ix":11}},"ef":[],"shapes":[{"ty":"gr","bm":0,"hd":false,"mn":"ADBE Vector Group","nm":"Shape 1","ix":1,"cix":2,"np":3,"it":[{"ty":"sh","bm":0,"hd":false,"mn":"ADBE Vector Shape - Group","nm":"Path 1","ix":1,"d":1,"ks":{"a":0,"k":{"c":true,"i":[[18.5,10.5],[10.75,-22.25],[-40.5,-1.5],[54,-16.5],[24.75,0],[29,-2.5]],"o":[[-18.5,-10.5],[-10.75,22.25],[40.5,1.5],[-54,16.5],[-14.5,-0.25],[-29,2.5]],"v":[[-234.5,-43.25],[-275.5,-16.75],[28.5,12],[66,-41.75],[-63.25,-38.5],[-130.75,-27.75]]},"ix":2}},{"ty":"fl","bm":0,"hd":false,"mn":"ADBE Vector Graphic - Fill","nm":"Fill 1","c":{"a":0,"k":[1,0,0],"ix":4},"r":1,"o":{"a":0,"k":100,"ix":5}},{"ty":"tr","a":{"a":0,"k":[0,0],"ix":1},"s":{"a":0,"k":[100,100],"ix":3},"sk":{"a":0,"k":0,"ix":4},"p":{"a":0,"k":[0,0],"ix":2},"r":{"a":0,"k":0,"ix":6},"sa":{"a":0,"k":0,"ix":5},"o":{"a":0,"k":100,"ix":7}}]}],"ind":1},{"ty":4,"nm":"boat Outlines 2","sr":1,"st":96,"op":192,"ip":96,"hd":false,"ddd":0,"bm":0,"tt":2,"hasMask":false,"ao":0,"ks":{"a":{"a":0,"k":[87.819,63.661,0],"ix":1},"s":{"a":0,"k":[100,100,100],"ix":6},"sk":{"a":0,"k":0},"p":{"a":1,"k":[{"o":{"x":0.333,"y":0},"i":{"x":0.585,"y":1},"s":[187.697,115.319,0],"t":96,"ti":[0,0,0],"to":[0,0.792,0]},{"o":{"x":0.428,"y":0},"i":{"x":0.667,"y":1},"s":[187.697,120.069,0],"t":144,"ti":[0,0.792,0],"to":[0,0,0]},{"s":[187.697,115.319,0],"t":192}],"ix":2},"r":{"a":1,"k":[{"o":{"x":0.333,"y":0},"i":{"x":0.667,"y":1},"s":[0],"t":96},{"o":{"x":0.333,"y":0},"i":{"x":0.833,"y":0.83},"s":[1],"t":119},{"o":{"x":0.167,"y":0.163},"i":{"x":0.667,"y":1},"s":[0],"t":144},{"o":{"x":0.333,"y":0},"i":{"x":0.667,"y":1},"s":[-1],"t":168},{"s":[0],"t":192}],"ix":10},"sa":{"a":0,"k":0},"o":{"a":0,"k":100,"ix":11}},"ef":[],"shapes":[{"ty":"gr","bm":0,"hd":false,"mn":"ADBE Vector Group","nm":"Group 1","ix":1,"cix":2,"np":2,"it":[{"ty":"sh","bm":0,"hd":false,"mn":"ADBE Vector Shape - Group","nm":"Path 1","ix":1,"d":1,"ks":{"a":1,"k":[{"o":{"x":0.333,"y":0},"i":{"x":0.667,"y":1},"s":[{"c":false,"i":[[0,0],[0,0],[-59.173,32.798]],"o":[[0,0],[0,0],[0,0]],"v":[[-85.493,-12.099],[-71.387,-20.7],[85.493,-12.099]]}],"t":96},{"o":{"x":0.333,"y":0},"i":{"x":0.667,"y":1},"s":[{"c":false,"i":[[0,0],[0,0],[-59.173,32.798]],"o":[[0,0],[0,0],[0,0]],"v":[[-83.868,-14.599],[-71.387,-20.7],[85.493,-12.099]]}],"t":144},{"s":[{"c":false,"i":[[0,0],[0,0],[-59.173,32.798]],"o":[[0,0],[0,0],[0,0]],"v":[[-85.493,-12.099],[-71.387,-20.7],[85.493,-12.099]]}],"t":192}],"ix":2}},{"ty":"st","bm":0,"hd":false,"mn":"ADBE Vector Graphic - Stroke","nm":"Stroke 1","lc":2,"lj":2,"ml":1,"o":{"a":0,"k":100,"ix":4},"w":{"a":0,"k":1,"ix":5},"c":{"a":0,"k":[0.7373,0.8667,0.8902],"ix":3}},{"ty":"tr","a":{"a":0,"k":[0,0],"ix":1},"s":{"a":0,"k":[100,100],"ix":3},"sk":{"a":0,"k":0,"ix":4},"p":{"a":0,"k":[88.037,43.083],"ix":2},"r":{"a":0,"k":0,"ix":6},"sa":{"a":0,"k":0,"ix":5},"o":{"a":0,"k":100,"ix":7}}]},{"ty":"gr","bm":0,"hd":false,"mn":"ADBE Vector Group","nm":"Group 2","ix":2,"cix":2,"np":2,"it":[{"ty":"sh","bm":0,"hd":false,"mn":"ADBE Vector Shape - Group","nm":"Path 1","ix":1,"d":1,"ks":{"a":1,"k":[{"o":{"x":0.333,"y":0},"i":{"x":0.667,"y":1},"s":[{"c":true,"i":[[0,0],[0,0],[-0.689,0],[0,0],[0,0]],"o":[[0,0],[-0.114,-0.688],[0,0],[0,0],[0,0]],"v":[[3.039,28.326],[-4.989,-27.752],[-3.956,-28.899],[-1.089,-28.899],[5.103,28.899]]}],"t":96},{"o":{"x":0.333,"y":0},"i":{"x":0.667,"y":1},"s":[{"c":true,"i":[[0,0],[0,0],[-0.689,0],[0,0],[0,0]],"o":[[0,0],[-0.114,-0.688],[0,0],[0,0],[0,0]],"v":[[3.039,28.326],[-4.989,-28.689],[-3.956,-29.837],[-1.089,-28.899],[5.103,28.899]]}],"t":144},{"s":[{"c":true,"i":[[0,0],[0,0],[-0.689,0],[0,0],[0,0]],"o":[[0,0],[-0.114,-0.688],[0,0],[0,0],[0,0]],"v":[[3.039,28.326],[-4.989,-27.752],[-3.956,-28.899],[-1.089,-28.899],[5.103,28.899]]}],"t":192}],"ix":2}},{"ty":"fl","bm":0,"hd":false,"mn":"ADBE Vector Graphic - Fill","nm":"Fill 1","c":{"a":0,"k":[0.7373,0.8667,0.8902],"ix":4},"r":1,"o":{"a":0,"k":100,"ix":5}},{"ty":"tr","a":{"a":0,"k":[0,0],"ix":1},"s":{"a":0,"k":[100,100],"ix":3},"sk":{"a":0,"k":0,"ix":4},"p":{"a":0,"k":[17.739,29.149],"ix":2},"r":{"a":0,"k":0,"ix":6},"sa":{"a":0,"k":0,"ix":5},"o":{"a":0,"k":100,"ix":7}}]},{"ty":"gr","bm":0,"hd":false,"mn":"ADBE Vector Group","nm":"Group 3","ix":3,"cix":2,"np":2,"it":[{"ty":"sh","bm":0,"hd":false,"mn":"ADBE Vector Shape - Group","nm":"Path 1","ix":1,"d":1,"ks":{"a":1,"k":[{"o":{"x":0.333,"y":0},"i":{"x":0.667,"y":1},"s":[{"c":true,"i":[[-63.876,31.766],[0,0],[58.027,15.597],[0,0],[0,0],[0,0]],"o":[[0,0],[0,0],[0,0],[0,0],[0,0],[0,0]],"v":[[87.271,-16.17],[65.482,9.863],[-66.743,11.812],[-70.413,10.207],[-87.271,-18.463],[-70.986,-27.409]]}],"t":96},{"o":{"x":0.333,"y":0},"i":{"x":0.667,"y":1},"s":[{"c":true,"i":[[-63.876,31.766],[0,0],[58.027,15.597],[0,0],[0,0],[0,0]],"o":[[0,0],[0,0],[0,0],[0,0],[0,0],[0,0]],"v":[[87.271,-16.17],[64.482,6.363],[-66.743,11.812],[-71.413,6.707],[-85.271,-20.588],[-70.986,-27.409]]}],"t":144},{"s":[{"c":true,"i":[[-63.876,31.766],[0,0],[58.027,15.597],[0,0],[0,0],[0,0]],"o":[[0,0],[0,0],[0,0],[0,0],[0,0],[0,0]],"v":[[87.271,-16.17],[65.482,9.863],[-66.743,11.812],[-70.413,10.207],[-87.271,-18.463],[-70.986,-27.409]]}],"t":192}],"ix":2}},{"ty":"fl","bm":0,"hd":false,"mn":"ADBE Vector Graphic - Fill","nm":"Fill 1","c":{"a":0,"k":[0.102,0.549,0.6275],"ix":4},"r":1,"o":{"a":0,"k":100,"ix":5}},{"ty":"tr","a":{"a":0,"k":[0,0],"ix":1},"s":{"a":0,"k":[100,100],"ix":3},"sk":{"a":0,"k":0,"ix":4},"p":{"a":0,"k":[87.521,45.663],"ix":2},"r":{"a":0,"k":0,"ix":6},"sa":{"a":0,"k":0,"ix":5},"o":{"a":0,"k":100,"ix":7}}]},{"ty":"gr","bm":0,"hd":false,"mn":"ADBE Vector Group","nm":"Group 4","ix":4,"cix":2,"np":2,"it":[{"ty":"sh","bm":0,"hd":false,"mn":"ADBE Vector Shape - Group","nm":"Path 1","ix":1,"d":1,"ks":{"a":1,"k":[{"o":{"x":0.333,"y":0},"i":{"x":0.667,"y":1},"s":[{"c":true,"i":[[0,0],[-27.752,7.111],[3.095,-7.569],[0,0],[0,0]],"o":[[0,0],[27.752,-7.11],[0,0],[0,0],[0,0]],"v":[[-53.555,1.663],[-5.161,-7.053],[50.46,-4.415],[37.844,5.562],[-40.711,14.163]]}],"t":96},{"o":{"x":0.333,"y":0},"i":{"x":0.667,"y":1},"s":[{"c":true,"i":[[0,0],[-27.752,7.111],[3.095,-7.569],[0,0],[0,0]],"o":[[0,0],[27.752,-7.11],[0,0],[0,0],[0,0]],"v":[[-53.555,1.663],[-6.786,-10.178],[50.46,-4.415],[37.844,5.562],[-40.711,14.163]]}],"t":144},{"s":[{"c":true,"i":[[0,0],[-27.752,7.111],[3.095,-7.569],[0,0],[0,0]],"o":[[0,0],[27.752,-7.11],[0,0],[0,0],[0,0]],"v":[[-53.555,1.663],[-5.161,-7.053],[50.46,-4.415],[37.844,5.562],[-40.711,14.163]]}],"t":192}],"ix":2}},{"ty":"fl","bm":0,"hd":false,"mn":"ADBE Vector Graphic - Fill","nm":"Fill 1","c":{"a":0,"k":[0.7373,0.8667,0.8902],"ix":4},"r":1,"o":{"a":0,"k":100,"ix":5}},{"ty":"tr","a":{"a":0,"k":[0,0],"ix":1},"s":{"a":0,"k":[100,100],"ix":3},"sk":{"a":0,"k":0,"ix":4},"p":{"a":0,"k":[124.333,33.909],"ix":2},"r":{"a":0,"k":0,"ix":6},"sa":{"a":0,"k":0,"ix":5},"o":{"a":0,"k":100,"ix":7}}]},{"ty":"gr","bm":0,"hd":false,"mn":"ADBE Vector Group","nm":"Group 5","ix":5,"cix":2,"np":2,"it":[{"ty":"sh","bm":0,"hd":false,"mn":"ADBE Vector Shape - Group","nm":"Path 1","ix":1,"d":1,"ks":{"a":1,"k":[{"o":{"x":0.333,"y":0},"i":{"x":0.667,"y":1},"s":[{"c":true,"i":[[0,0],[-2.523,-20.871],[0,0]],"o":[[0,0],[2.523,20.872],[0,0]],"v":[[-8.658,-26.605],[6.135,5.734],[-5.447,3.326]]}],"t":96},{"o":{"x":0.333,"y":0},"i":{"x":0.667,"y":1},"s":[{"c":true,"i":[[0,0],[-2.523,-20.871],[0,0]],"o":[[0,0],[2.523,20.872],[0,0]],"v":[[-8.658,-26.605],[8.01,5.484],[-5.447,3.326]]}],"t":144},{"s":[{"c":true,"i":[[0,0],[-2.523,-20.871],[0,0]],"o":[[0,0],[2.523,20.872],[0,0]],"v":[[-8.658,-26.605],[6.135,5.734],[-5.447,3.326]]}],"t":192}],"ix":2}},{"ty":"fl","bm":0,"hd":false,"mn":"ADBE Vector Graphic - Fill","nm":"Fill 1","c":{"a":0,"k":[0.7373,0.8667,0.8902],"ix":4},"r":1,"o":{"a":0,"k":100,"ix":5}},{"ty":"tr","a":{"a":0,"k":[0,0],"ix":1},"s":{"a":0,"k":[100,100],"ix":3},"sk":{"a":0,"k":0,"ix":4},"p":{"a":0,"k":[25.308,26.856],"ix":2},"r":{"a":0,"k":0,"ix":6},"sa":{"a":0,"k":0,"ix":5},"o":{"a":0,"k":100,"ix":7}}]}],"ind":2},{"ty":4,"nm":"Shape Layer 1","sr":1,"st":0,"op":96,"ip":0,"hd":false,"ddd":0,"bm":0,"hasMask":false,"td":1,"ao":0,"ks":{"a":{"a":0,"k":[0,0,0],"ix":1},"s":{"a":0,"k":[100,100,100],"ix":6},"sk":{"a":0,"k":0},"p":{"a":1,"k":[{"o":{"x":0.333,"y":0},"i":{"x":0.667,"y":1},"s":[187.5,152.25,0],"t":0,"ti":[-22.667,0.083,0],"to":[22.667,-0.083,0]},{"s":[323.5,151.75,0],"t":78}],"ix":2},"r":{"a":0,"k":0,"ix":10},"sa":{"a":0,"k":0},"o":{"a":0,"k":100,"ix":11}},"ef":[],"shapes":[{"ty":"gr","bm":0,"hd":false,"mn":"ADBE Vector Group","nm":"Shape 1","ix":1,"cix":2,"np":3,"it":[{"ty":"sh","bm":0,"hd":false,"mn":"ADBE Vector Shape - Group","nm":"Path 1","ix":1,"d":1,"ks":{"a":0,"k":{"c":true,"i":[[18.5,10.5],[10.75,-22.25],[-40.5,-1.5],[54,-16.5],[24.75,0],[29,-2.5]],"o":[[-18.5,-10.5],[-10.75,22.25],[40.5,1.5],[-54,16.5],[-14.5,-0.25],[-29,2.5]],"v":[[-234.5,-43.25],[-275.5,-16.75],[28.5,12],[66,-41.75],[-63.25,-38.5],[-130.75,-27.75]]},"ix":2}},{"ty":"fl","bm":0,"hd":false,"mn":"ADBE Vector Graphic - Fill","nm":"Fill 1","c":{"a":0,"k":[1,0,0],"ix":4},"r":1,"o":{"a":0,"k":100,"ix":5}},{"ty":"tr","a":{"a":0,"k":[0,0],"ix":1},"s":{"a":0,"k":[100,100],"ix":3},"sk":{"a":0,"k":0,"ix":4},"p":{"a":0,"k":[0,0],"ix":2},"r":{"a":0,"k":0,"ix":6},"sa":{"a":0,"k":0,"ix":5},"o":{"a":0,"k":100,"ix":7}}]}],"ind":3},{"ty":4,"nm":"boat Outlines","sr":1,"st":0,"op":96,"ip":0,"hd":false,"ddd":0,"bm":0,"tt":2,"hasMask":false,"ao":0,"ks":{"a":{"a":0,"k":[87.819,63.661,0],"ix":1},"s":{"a":0,"k":[100,100,100],"ix":6},"sk":{"a":0,"k":0},"p":{"a":1,"k":[{"o":{"x":0.333,"y":0},"i":{"x":0.585,"y":1},"s":[187.697,115.319,0],"t":0,"ti":[0,0,0],"to":[0,0.792,0]},{"o":{"x":0.428,"y":0},"i":{"x":0.667,"y":1},"s":[187.697,120.069,0],"t":48,"ti":[0,0.792,0],"to":[0,0,0]},{"s":[187.697,115.319,0],"t":96}],"ix":2},"r":{"a":1,"k":[{"o":{"x":0.333,"y":0},"i":{"x":0.667,"y":1},"s":[0],"t":0},{"o":{"x":0.333,"y":0},"i":{"x":0.833,"y":0.83},"s":[1],"t":23},{"o":{"x":0.167,"y":0.163},"i":{"x":0.667,"y":1},"s":[0],"t":48},{"o":{"x":0.333,"y":0},"i":{"x":0.667,"y":1},"s":[-1],"t":72},{"s":[0],"t":96}],"ix":10},"sa":{"a":0,"k":0},"o":{"a":0,"k":100,"ix":11}},"ef":[],"shapes":[{"ty":"gr","bm":0,"hd":false,"mn":"ADBE Vector Group","nm":"Group 1","ix":1,"cix":2,"np":2,"it":[{"ty":"sh","bm":0,"hd":false,"mn":"ADBE Vector Shape - Group","nm":"Path 1","ix":1,"d":1,"ks":{"a":1,"k":[{"o":{"x":0.333,"y":0},"i":{"x":0.667,"y":1},"s":[{"c":false,"i":[[0,0],[0,0],[-59.173,32.798]],"o":[[0,0],[0,0],[0,0]],"v":[[-85.493,-12.099],[-71.387,-20.7],[85.493,-12.099]]}],"t":0},{"o":{"x":0.333,"y":0},"i":{"x":0.667,"y":1},"s":[{"c":false,"i":[[0,0],[0,0],[-59.173,32.798]],"o":[[0,0],[0,0],[0,0]],"v":[[-83.868,-14.599],[-71.387,-20.7],[85.493,-12.099]]}],"t":48},{"s":[{"c":false,"i":[[0,0],[0,0],[-59.173,32.798]],"o":[[0,0],[0,0],[0,0]],"v":[[-85.493,-12.099],[-71.387,-20.7],[85.493,-12.099]]}],"t":96}],"ix":2}},{"ty":"st","bm":0,"hd":false,"mn":"ADBE Vector Graphic - Stroke","nm":"Stroke 1","lc":2,"lj":2,"ml":1,"o":{"a":0,"k":100,"ix":4},"w":{"a":0,"k":1,"ix":5},"c":{"a":0,"k":[0.7373,0.8667,0.8902],"ix":3}},{"ty":"tr","a":{"a":0,"k":[0,0],"ix":1},"s":{"a":0,"k":[100,100],"ix":3},"sk":{"a":0,"k":0,"ix":4},"p":{"a":0,"k":[88.037,43.083],"ix":2},"r":{"a":0,"k":0,"ix":6},"sa":{"a":0,"k":0,"ix":5},"o":{"a":0,"k":100,"ix":7}}]},{"ty":"gr","bm":0,"hd":false,"mn":"ADBE Vector Group","nm":"Group 2","ix":2,"cix":2,"np":2,"it":[{"ty":"sh","bm":0,"hd":false,"mn":"ADBE Vector Shape - Group","nm":"Path 1","ix":1,"d":1,"ks":{"a":1,"k":[{"o":{"x":0.333,"y":0},"i":{"x":0.667,"y":1},"s":[{"c":true,"i":[[0,0],[0,0],[-0.689,0],[0,0],[0,0]],"o":[[0,0],[-0.114,-0.688],[0,0],[0,0],[0,0]],"v":[[3.039,28.326],[-4.989,-27.752],[-3.956,-28.899],[-1.089,-28.899],[5.103,28.899]]}],"t":0},{"o":{"x":0.333,"y":0},"i":{"x":0.667,"y":1},"s":[{"c":true,"i":[[0,0],[0,0],[-0.689,0],[0,0],[0,0]],"o":[[0,0],[-0.114,-0.688],[0,0],[0,0],[0,0]],"v":[[3.039,28.326],[-4.989,-28.689],[-3.956,-29.837],[-1.089,-28.899],[5.103,28.899]]}],"t":48},{"s":[{"c":true,"i":[[0,0],[0,0],[-0.689,0],[0,0],[0,0]],"o":[[0,0],[-0.114,-0.688],[0,0],[0,0],[0,0]],"v":[[3.039,28.326],[-4.989,-27.752],[-3.956,-28.899],[-1.089,-28.899],[5.103,28.899]]}],"t":96}],"ix":2}},{"ty":"fl","bm":0,"hd":false,"mn":"ADBE Vector Graphic - Fill","nm":"Fill 1","c":{"a":0,"k":[0.7373,0.8667,0.8902],"ix":4},"r":1,"o":{"a":0,"k":100,"ix":5}},{"ty":"tr","a":{"a":0,"k":[0,0],"ix":1},"s":{"a":0,"k":[100,100],"ix":3},"sk":{"a":0,"k":0,"ix":4},"p":{"a":0,"k":[17.739,29.149],"ix":2},"r":{"a":0,"k":0,"ix":6},"sa":{"a":0,"k":0,"ix":5},"o":{"a":0,"k":100,"ix":7}}]},{"ty":"gr","bm":0,"hd":false,"mn":"ADBE Vector Group","nm":"Group 3","ix":3,"cix":2,"np":2,"it":[{"ty":"sh","bm":0,"hd":false,"mn":"ADBE Vector Shape - Group","nm":"Path 1","ix":1,"d":1,"ks":{"a":1,"k":[{"o":{"x":0.333,"y":0},"i":{"x":0.667,"y":1},"s":[{"c":true,"i":[[-63.876,31.766],[0,0],[58.027,15.597],[0,0],[0,0],[0,0]],"o":[[0,0],[0,0],[0,0],[0,0],[0,0],[0,0]],"v":[[87.271,-16.17],[65.482,9.863],[-66.743,11.812],[-70.413,10.207],[-87.271,-18.463],[-70.986,-27.409]]}],"t":0},{"o":{"x":0.333,"y":0},"i":{"x":0.667,"y":1},"s":[{"c":true,"i":[[-63.876,31.766],[0,0],[58.027,15.597],[0,0],[0,0],[0,0]],"o":[[0,0],[0,0],[0,0],[0,0],[0,0],[0,0]],"v":[[87.271,-16.17],[64.482,6.363],[-66.743,11.812],[-71.413,6.707],[-85.271,-20.588],[-70.986,-27.409]]}],"t":48},{"s":[{"c":true,"i":[[-63.876,31.766],[0,0],[58.027,15.597],[0,0],[0,0],[0,0]],"o":[[0,0],[0,0],[0,0],[0,0],[0,0],[0,0]],"v":[[87.271,-16.17],[65.482,9.863],[-66.743,11.812],[-70.413,10.207],[-87.271,-18.463],[-70.986,-27.409]]}],"t":96}],"ix":2}},{"ty":"fl","bm":0,"hd":false,"mn":"ADBE Vector Graphic - Fill","nm":"Fill 1","c":{"a":0,"k":[0.102,0.549,0.6275],"ix":4},"r":1,"o":{"a":0,"k":100,"ix":5}},{"ty":"tr","a":{"a":0,"k":[0,0],"ix":1},"s":{"a":0,"k":[100,100],"ix":3},"sk":{"a":0,"k":0,"ix":4},"p":{"a":0,"k":[87.521,45.663],"ix":2},"r":{"a":0,"k":0,"ix":6},"sa":{"a":0,"k":0,"ix":5},"o":{"a":0,"k":100,"ix":7}}]},{"ty":"gr","bm":0,"hd":false,"mn":"ADBE Vector Group","nm":"Group 4","ix":4,"cix":2,"np":2,"it":[{"ty":"sh","bm":0,"hd":false,"mn":"ADBE Vector Shape - Group","nm":"Path 1","ix":1,"d":1,"ks":{"a":1,"k":[{"o":{"x":0.333,"y":0},"i":{"x":0.667,"y":1},"s":[{"c":true,"i":[[0,0],[-27.752,7.111],[3.095,-7.569],[0,0],[0,0]],"o":[[0,0],[27.752,-7.11],[0,0],[0,0],[0,0]],"v":[[-53.555,1.663],[-5.161,-7.053],[50.46,-4.415],[37.844,5.562],[-40.711,14.163]]}],"t":0},{"o":{"x":0.333,"y":0},"i":{"x":0.667,"y":1},"s":[{"c":true,"i":[[0,0],[-27.752,7.111],[3.095,-7.569],[0,0],[0,0]],"o":[[0,0],[27.752,-7.11],[0,0],[0,0],[0,0]],"v":[[-53.555,1.663],[-6.786,-10.178],[50.46,-4.415],[37.844,5.562],[-40.711,14.163]]}],"t":48},{"s":[{"c":true,"i":[[0,0],[-27.752,7.111],[3.095,-7.569],[0,0],[0,0]],"o":[[0,0],[27.752,-7.11],[0,0],[0,0],[0,0]],"v":[[-53.555,1.663],[-5.161,-7.053],[50.46,-4.415],[37.844,5.562],[-40.711,14.163]]}],"t":96}],"ix":2}},{"ty":"fl","bm":0,"hd":false,"mn":"ADBE Vector Graphic - Fill","nm":"Fill 1","c":{"a":0,"k":[0.7373,0.8667,0.8902],"ix":4},"r":1,"o":{"a":0,"k":100,"ix":5}},{"ty":"tr","a":{"a":0,"k":[0,0],"ix":1},"s":{"a":0,"k":[100,100],"ix":3},"sk":{"a":0,"k":0,"ix":4},"p":{"a":0,"k":[124.333,33.909],"ix":2},"r":{"a":0,"k":0,"ix":6},"sa":{"a":0,"k":0,"ix":5},"o":{"a":0,"k":100,"ix":7}}]},{"ty":"gr","bm":0,"hd":false,"mn":"ADBE Vector Group","nm":"Group 5","ix":5,"cix":2,"np":2,"it":[{"ty":"sh","bm":0,"hd":false,"mn":"ADBE Vector Shape - Group","nm":"Path 1","ix":1,"d":1,"ks":{"a":1,"k":[{"o":{"x":0.333,"y":0},"i":{"x":0.667,"y":1},"s":[{"c":true,"i":[[0,0],[-2.523,-20.871],[0,0]],"o":[[0,0],[2.523,20.872],[0,0]],"v":[[-8.658,-26.605],[6.135,5.734],[-5.447,3.326]]}],"t":0},{"o":{"x":0.333,"y":0},"i":{"x":0.667,"y":1},"s":[{"c":true,"i":[[0,0],[-2.523,-20.871],[0,0]],"o":[[0,0],[2.523,20.872],[0,0]],"v":[[-8.658,-26.605],[8.01,5.484],[-5.447,3.326]]}],"t":48},{"s":[{"c":true,"i":[[0,0],[-2.523,-20.871],[0,0]],"o":[[0,0],[2.523,20.872],[0,0]],"v":[[-8.658,-26.605],[6.135,5.734],[-5.447,3.326]]}],"t":96}],"ix":2}},{"ty":"fl","bm":0,"hd":false,"mn":"ADBE Vector Graphic - Fill","nm":"Fill 1","c":{"a":0,"k":[0.7373,0.8667,0.8902],"ix":4},"r":1,"o":{"a":0,"k":100,"ix":5}},{"ty":"tr","a":{"a":0,"k":[0,0],"ix":1},"s":{"a":0,"k":[100,100],"ix":3},"sk":{"a":0,"k":0,"ix":4},"p":{"a":0,"k":[25.308,26.856],"ix":2},"r":{"a":0,"k":0,"ix":6},"sa":{"a":0,"k":0,"ix":5},"o":{"a":0,"k":100,"ix":7}}]}],"ind":4},{"ty":4,"nm":"reflection Outlines","sr":1,"st":0,"op":234,"ip":0,"hd":false,"ddd":0,"bm":0,"hasMask":false,"ao":0,"ks":{"a":{"a":0,"k":[83.286,16.438,0],"ix":1},"s":{"a":0,"k":[100,100,100],"ix":6},"sk":{"a":0,"k":0},"p":{"a":1,"k":[{"o":{"x":0.333,"y":0},"i":{"x":0.667,"y":1},"s":[183.415,119.053,0],"t":0,"ti":[0,0,0],"to":[0,-0.333,0]},{"o":{"x":0.333,"y":0},"i":{"x":0.667,"y":1},"s":[183.415,117.053,0],"t":48,"ti":[0,0,0],"to":[0,0,0]},{"o":{"x":0.333,"y":0},"i":{"x":0.667,"y":1},"s":[183.415,119.053,0],"t":96,"ti":[0,0,0],"to":[0,0,0]},{"o":{"x":0.333,"y":0},"i":{"x":0.667,"y":1},"s":[183.415,117.053,0],"t":144,"ti":[0,-0.333,0],"to":[0,0,0]},{"s":[183.415,119.053,0],"t":192}],"ix":2},"r":{"a":1,"k":[{"o":{"x":0.333,"y":0},"i":{"x":0.667,"y":1},"s":[0],"t":0},{"o":{"x":0.333,"y":0},"i":{"x":0.833,"y":0.83},"s":[-1],"t":23},{"o":{"x":0.167,"y":0.163},"i":{"x":0.667,"y":1},"s":[0],"t":48},{"o":{"x":0.333,"y":0},"i":{"x":0.667,"y":1},"s":[1],"t":72},{"o":{"x":0.333,"y":0},"i":{"x":0.667,"y":1},"s":[0],"t":96},{"o":{"x":0.333,"y":0},"i":{"x":0.833,"y":0.833},"s":[-1],"t":119},{"o":{"x":0.167,"y":0.16},"i":{"x":0.667,"y":1},"s":[0],"t":144},{"o":{"x":0.333,"y":0},"i":{"x":0.667,"y":1},"s":[1],"t":168},{"s":[0],"t":192}],"ix":10},"sa":{"a":0,"k":0},"o":{"a":0,"k":25,"ix":11}},"ef":[],"shapes":[{"ty":"gr","bm":0,"hd":false,"mn":"ADBE Vector Group","nm":"Group 1","ix":1,"cix":2,"np":2,"it":[{"ty":"sh","bm":0,"hd":false,"mn":"ADBE Vector Shape - Group","nm":"Path 1","ix":1,"d":1,"ks":{"a":0,"k":{"c":true,"i":[[2.065,1.95],[0,0],[58.027,-12.385],[0,0],[0,0],[0,0],[-10.665,2.982],[-46.33,-12.729]],"o":[[0,0],[0,0],[0,0],[0,0],[0,0],[10.092,4.358],[27.293,-7.683],[2.752,0.803]],"v":[[82.424,2.237],[69.466,-9.804],[-62.759,-11.295],[-65.282,-11.639],[-83.287,12.329],[-83.287,12.558],[-51.291,14.622],[79.787,6.824]]},"ix":2}},{"ty":"fl","bm":0,"hd":false,"mn":"ADBE Vector Graphic - Fill","nm":"Fill 1","c":{"a":0,"k":[0.0941,0.3451,0.3922],"ix":4},"r":1,"o":{"a":0,"k":100,"ix":5}},{"ty":"tr","a":{"a":0,"k":[0,0],"ix":1},"s":{"a":0,"k":[100,100],"ix":3},"sk":{"a":0,"k":0,"ix":4},"p":{"a":0,"k":[83.286,16.438],"ix":2},"r":{"a":0,"k":0,"ix":6},"sa":{"a":0,"k":0,"ix":5},"o":{"a":0,"k":100,"ix":7}}]}],"ind":5},{"ty":4,"nm":"bg Outlines","sr":1,"st":0,"op":345,"ip":0,"hd":false,"ddd":0,"bm":0,"hasMask":false,"ao":0,"ks":{"a":{"a":0,"k":[187.75,151.5,0],"ix":1},"s":{"a":0,"k":[100,100,100],"ix":6},"sk":{"a":0,"k":0},"p":{"a":0,"k":[187.5,151.251,0],"ix":2},"r":{"a":0,"k":0,"ix":10},"sa":{"a":0,"k":0},"o":{"a":0,"k":100,"ix":11}},"ef":[],"shapes":[{"ty":"gr","bm":0,"hd":false,"mn":"ADBE Vector Group","nm":"Group 1","ix":1,"cix":2,"np":2,"it":[{"ty":"sh","bm":0,"hd":false,"mn":"ADBE Vector Shape - Group","nm":"Path 1","ix":1,"d":1,"ks":{"a":0,"k":{"c":true,"i":[[0,0],[-86.635,10.374],[0,0],[0,0],[0,0]],"o":[[0,0],[98.797,-11.83],[0,0],[0,0],[0,0]],"v":[[-187.5,-80.826],[49.885,-75.089],[187.5,-87.711],[187.5,90.785],[-187.5,90.785]]},"ix":2}},{"ty":"fl","bm":0,"hd":false,"mn":"ADBE Vector Graphic - Fill","nm":"Fill 1","c":{"a":0,"k":[0.1961,0.7216,0.8118],"ix":4},"r":1,"o":{"a":0,"k":100,"ix":5}},{"ty":"tr","a":{"a":0,"k":[0,0],"ix":1},"s":{"a":0,"k":[100,100],"ix":3},"sk":{"a":0,"k":0,"ix":4},"p":{"a":0,"k":[187.75,211.964],"ix":2},"r":{"a":0,"k":0,"ix":6},"sa":{"a":0,"k":0,"ix":5},"o":{"a":0,"k":100,"ix":7}}]},{"ty":"gr","bm":0,"hd":false,"mn":"ADBE Vector Group","nm":"Group 2","ix":2,"cix":2,"np":2,"it":[{"ty":"sh","bm":0,"hd":false,"mn":"ADBE Vector Shape - Group","nm":"Path 1","ix":1,"d":1,"ks":{"a":0,"k":{"c":true,"i":[[0,0],[0,0],[0,0],[0,0]],"o":[[0,0],[0,0],[0,0],[0,0]],"v":[[-187.5,69.999],[187.5,69.999],[187.5,-69.999],[-187.5,-69.999]]},"ix":2}},{"ty":"fl","bm":0,"hd":false,"mn":"ADBE Vector Graphic - Fill","nm":"Fill 1","c":{"a":0,"k":[0.1961,0.7216,0.8118],"ix":4},"r":1,"o":{"a":0,"k":100,"ix":5}},{"ty":"tr","a":{"a":0,"k":[0,0],"ix":1},"s":{"a":0,"k":[100,100],"ix":3},"sk":{"a":0,"k":0,"ix":4},"p":{"a":0,"k":[187.75,70.249],"ix":2},"r":{"a":0,"k":0,"ix":6},"sa":{"a":0,"k":0,"ix":5},"o":{"a":0,"k":100,"ix":7}}]}],"ind":6}],"v":"5.6.8","fr":12,"op":192,"ip":0,"assets":[]}